swaggeraemosgi
