Metadata-Version: 1.2
Name: swaggeraemosgi
Version: 1.0.0
Summary: Adobe Experience Manager OSGI config (AEM) API
Home-page: https://github.com/shinesolutions/swagger-aem-osgi/tree/master/python
Author: Shine Solutions
Author-email: opensource@shinesolutions.com
License: UNKNOWN
Keywords: OpenAPI,OpenAPI-Generator,Adobe Experience Manager OSGI config (AEM) API
Platform: UNKNOWN
Requires-Python: >=3.6
